[
  {
    "mods": "FM1",
    "defaultMagnification": 1,
    "requestValue": 1,
    "bonusMods": ""
  },
  {
    "mods": "FM2",
    "defaultMagnification": 1,
    "requestValue": 1,
    "bonusMods": ""
  },
  {
    "mods": "FM3",
    "defaultMagnification": 1,
    "requestValue": 2,
    "bonusMods": "ST"
  },
  {
    "mods": "FM4",
    "defaultMagnification": 1,
    "requestValue": 2,
    "bonusMods": "AL"
  },
  {
    "mods": "FM5",
    "defaultMagnification": 1,
    "requestValue": -1,
    "bonusMods": ""
  },
  {
    "mods": "FM6",
    "defaultMagnification": 1,
    "requestValue": 0,
    "bonusMods": ""
  },
  {
    "mods": "FM7",
    "defaultMagnification": 1,
    "requestValue": 0,
    "bonusMods": ""
  },
  {
    "mods": "TB",
    "defaultMagnification": 1,
    "requestValue": 0,
    "bonusMods": ""
  }
]
